.editorconfig
.gitignore
.gitlab-ci.yml
README.rst
publish.settings.sh
publish.sh
pyproject.toml
tsconfig.json
.idea/modules.xml
.idea/peek-abstract-chunked-data-loader.iml
.idea/inspectionProfiles/Project_Default.xml
.idea/inspectionProfiles/profiles_settings.xml
peek_abstract_chunked_data_loader/PlatformDependencyTest.py
peek_abstract_chunked_data_loader/__init__.py
peek_abstract_chunked_data_loader.egg-info/PKG-INFO
peek_abstract_chunked_data_loader.egg-info/SOURCES.txt
peek_abstract_chunked_data_loader.egg-info/dependency_links.txt
peek_abstract_chunked_data_loader.egg-info/requires.txt
peek_abstract_chunked_data_loader.egg-info/top_level.txt
peek_abstract_chunked_data_loader/private/__init__.py
peek_abstract_chunked_data_loader/private/admin-app.abctodo/__init__.py
peek_abstract_chunked_data_loader/private/admin-app.abctodo/abstracDataLoader.component.html
peek_abstract_chunked_data_loader/private/admin-app.abctodo/abstracDataLoader.component.ts
peek_abstract_chunked_data_loader/private/admin-app.abctodo/edit-setting-table/edit.component.html
peek_abstract_chunked_data_loader/private/admin-app.abctodo/edit-setting-table/edit.component.ts
peek_abstract_chunked_data_loader/private/admin-app.abctodo/edit-source-settings/edit.component.html
peek_abstract_chunked_data_loader/private/admin-app.abctodo/edit-source-settings/edit.component.ts
peek_abstract_chunked_data_loader/private/admin-app.abctodo/status/status.component.html
peek_abstract_chunked_data_loader/private/admin-app.abctodo/status/status.component.ts
peek_abstract_chunked_data_loader/private/admin-app.abctodo/tuples/AppServerSettingsTuple.ts
peek_abstract_chunked_data_loader/private/admin-app.abctodo/tuples/LoaderStatusTuple.ts
peek_abstract_chunked_data_loader/private/admin-app.abctodo/tuples/SettingPropertyTuple.ts
peek_abstract_chunked_data_loader/private/agent/AgentController.py.abctodo
peek_abstract_chunked_data_loader/private/agent/AgentEntryHook.py.abctodo
peek_abstract_chunked_data_loader/private/agent/__init__.py
peek_abstract_chunked_data_loader/private/agent/imp/DataImportChunk.py.abctodo
peek_abstract_chunked_data_loader/private/agent/imp/DataImportChunks.py.abctodo
peek_abstract_chunked_data_loader/private/agent/imp/__init__.py
