Metadata-Version: 2.4
Name: peek-abstract-chunked-data-loader
Version: 5.0.4
Summary: Peek Plugin AbstractDataLoader - equipment detail loading from a source server
Author-email: Synerty <contact@synerty.com>
Project-URL: Homepage, https://github.com/Synerty/peek-abstract-chunked-data-loader
Keywords: Peek,Python,Platform,synerty
Requires-Dist: peek-plugin-base==5.0.4
